<data endPointMarkPosition="396|363">
  <info id="0010" name="亡者试炼场" dec="10"/>
  <waves>
    <wave duration="123213">
      <subWave startTime="0" duration="3000">
        <monster typeId="1232" count="3" roadIndex="0"/>
      </subWave>
    </wave>
  </waves>
  <roads>
    <road>
      <p x="375" y="-36"/>
      <p x="375" y="34"/>
      <p x="375" y="98"/>
      <p x="368" y="122"/>
      <p x="355" y="125"/>
      <p x="343" y="125"/>
      <p x="299" y="124"/>
      <p x="288" y="121"/>
      <p x="278" y="116"/>
      <p x="270" y="110"/>
      <p x="249" y="99"/>
      <p x="238" y="96"/>
      <p x="226" y="95"/>
      <p x="204" y="95"/>
      <p x="194" y="95"/>
      <p x="154" y="102"/>
      <p x="145" y="105"/>
      <p x="125" y="112"/>
      <p x="116" y="117"/>
      <p x="107" y="123"/>
      <p x="100" y="130"/>
      <p x="93" y="137"/>
      <p x="87" y="146"/>
      <p x="83" y="155"/>
      <p x="80" y="165"/>
      <p x="77" y="176"/>
      <p x="75" y="198"/>
      <p x="75" y="221"/>
      <p x="76" y="232"/>
      <p x="81" y="254"/>
      <p x="89" y="275"/>
      <p x="94" y="284"/>
      <p x="100" y="293"/>
      <p x="108" y="301"/>
      <p x="116" y="308"/>
      <p x="125" y="315"/>
      <p x="143" y="325"/>
      <p x="153" y="329"/>
      <p x="163" y="332"/>
      <p x="174" y="334"/>
      <p x="185" y="335"/>
      <p x="248" y="332"/>
      <p x="260" y="330"/>
      <p x="281" y="322"/>
      <p x="291" y="317"/>
      <p x="300" y="310"/>
      <p x="320" y="299"/>
      <p x="331" y="296"/>
      <p x="343" y="295"/>
      <p x="365" y="295"/>
      <p x="387" y="298"/>
      <p x="395" y="305"/>
      <p x="395" y="316"/>
      <p x="395" y="382"/>
      <p x="395" y="415"/>
    </road>
    <road>
      <p x="374" y="-36"/>
      <p x="374" y="37"/>
      <p x="376" y="101"/>
      <p x="380" y="112"/>
      <p x="386" y="122"/>
      <p x="395" y="130"/>
      <p x="404" y="135"/>
      <p x="415" y="139"/>
      <p x="427" y="141"/>
      <p x="438" y="141"/>
      <p x="450" y="140"/>
      <p x="510" y="130"/>
      <p x="575" y="125"/>
      <p x="585" y="125"/>
      <p x="615" y="130"/>
      <p x="655" y="140"/>
      <p x="678" y="148"/>
      <p x="690" y="155"/>
      <p x="697" y="161"/>
      <p x="703" y="170"/>
      <p x="707" y="179"/>
      <p x="710" y="190"/>
      <p x="713" y="209"/>
      <p x="715" y="240"/>
      <p x="713" y="262"/>
      <p x="710" y="285"/>
      <p x="706" y="295"/>
      <p x="699" y="304"/>
      <p x="690" y="310"/>
      <p x="678" y="313"/>
      <p x="635" y="322"/>
      <p x="624" y="322"/>
      <p x="605" y="320"/>
      <p x="593" y="317"/>
      <p x="582" y="313"/>
      <p x="572" y="308"/>
      <p x="565" y="300"/>
      <p x="543" y="286"/>
      <p x="530" y="285"/>
      <p x="518" y="285"/>
      <p x="445" y="285"/>
      <p x="424" y="286"/>
      <p x="415" y="290"/>
      <p x="402" y="305"/>
      <p x="397" y="324"/>
      <p x="396" y="334"/>
      <p x="395" y="355"/>
      <p x="395" y="415"/>
      <p x="395" y="425"/>
    </road>
    <road>
      <p x="399" y="678"/>
      <p x="395" y="605"/>
      <p x="385" y="540"/>
      <p x="378" y="532"/>
      <p x="369" y="526"/>
      <p x="360" y="522"/>
      <p x="350" y="520"/>
      <p x="327" y="516"/>
      <p x="305" y="515"/>
      <p x="265" y="515"/>
      <p x="252" y="514"/>
      <p x="240" y="515"/>
      <p x="155" y="515"/>
      <p x="93" y="513"/>
      <p x="82" y="508"/>
      <p x="75" y="500"/>
      <p x="67" y="487"/>
      <p x="57" y="465"/>
      <p x="55" y="455"/>
      <p x="55" y="435"/>
      <p x="57" y="412"/>
      <p x="60" y="400"/>
      <p x="64" y="390"/>
      <p x="70" y="380"/>
      <p x="83" y="360"/>
      <p x="91" y="352"/>
      <p x="100" y="345"/>
      <p x="109" y="339"/>
      <p x="130" y="330"/>
      <p x="141" y="327"/>
      <p x="153" y="327"/>
      <p x="165" y="330"/>
      <p x="220" y="334"/>
      <p x="230" y="334"/>
      <p x="270" y="327"/>
      <p x="281" y="322"/>
      <p x="291" y="317"/>
      <p x="300" y="310"/>
      <p x="318" y="298"/>
      <p x="329" y="295"/>
      <p x="340" y="295"/>
      <p x="350" y="295"/>
      <p x="360" y="297"/>
      <p x="370" y="300"/>
      <p x="380" y="305"/>
      <p x="389" y="314"/>
      <p x="393" y="326"/>
      <p x="395" y="340"/>
      <p x="395" y="350"/>
      <p x="395" y="414"/>
      <p x="395" y="425"/>
    </road>
    <road>
      <p x="397" y="678"/>
      <p x="395" y="605"/>
      <p x="398" y="560"/>
      <p x="402" y="549"/>
      <p x="410" y="540"/>
      <p x="418" y="532"/>
      <p x="428" y="527"/>
      <p x="439" y="522"/>
      <p x="450" y="520"/>
      <p x="459" y="518"/>
      <p x="480" y="517"/>
      <p x="490" y="518"/>
      <p x="509" y="521"/>
      <p x="550" y="525"/>
      <p x="610" y="524"/>
      <p x="640" y="521"/>
      <p x="697" y="507"/>
      <p x="705" y="495"/>
      <p x="709" y="485"/>
      <p x="712" y="475"/>
      <p x="714" y="465"/>
      <p x="715" y="455"/>
      <p x="713" y="389"/>
      <p x="711" y="379"/>
      <p x="705" y="360"/>
      <p x="700" y="350"/>
      <p x="694" y="342"/>
      <p x="687" y="335"/>
      <p x="679" y="329"/>
      <p x="670" y="325"/>
      <p x="659" y="321"/>
      <p x="647" y="318"/>
      <p x="636" y="318"/>
      <p x="625" y="320"/>
      <p x="601" y="319"/>
      <p x="590" y="315"/>
      <p x="580" y="310"/>
      <p x="523" y="287"/>
      <p x="512" y="286"/>
      <p x="440" y="285"/>
      <p x="429" y="286"/>
      <p x="419" y="289"/>
      <p x="410" y="296"/>
      <p x="405" y="305"/>
      <p x="400" y="315"/>
      <p x="397" y="326"/>
      <p x="395" y="338"/>
      <p x="395" y="350"/>
      <p x="395" y="414"/>
      <p x="395" y="425"/>
    </road>
  </roads>
  <elements>
    <Element category="Toft" x="321" y="379" meetPoint="-6|-69"/>
    <Element category="Toft" x="291" y="445" meetPoint="-6|63"/>
    <Element category="Toft" x="136" y="447" meetPoint="-69|9"/>
    <Element category="Toft" x="633" y="391" meetPoint="10|-63"/>
    <Element category="Toft" x="602" y="454" meetPoint="-4|64"/>
    <Element category="Toft" x="494" y="449" meetPoint="17|74"/>
    <Element category="Toft" x="641" y="250" meetPoint="-17|59"/>
    <Element category="Toft" x="280" y="190" meetPoint="9|-63"/>
    <Element category="Toft" x="484" y="208" meetPoint="-8|-65"/>
    <Element category="Toft" x="178" y="170" meetPoint="-24|-67"/>
    <Element category="Toft" x="163" y="249" meetPoint="-18|65"/>
    <Element category="Toft" x="322" y="580" meetPoint="-12|-60"/>
    <Element category="Toft" x="474" y="584" meetPoint="7|-60"/>
    <Element category="Toft" x="386" y="228" meetPoint="8|67"/>
    <Element category="Toft" x="254" y="257" meetPoint="6|59"/>
    <Element category="Toft" x="603" y="195" meetPoint="18|-54"/>
    <Element category="Toft" x="195" y="401" meetPoint="1|-62"/>
    <Element category="Toft" x="474" y="354" meetPoint="-12|-60"/>
  </elements>
</data>